<templateSet group="PHP">
  <template name="tryca" value="$trans = Yii::$app-&gt;db-&gt;beginTransaction();&#10;try {&#10;    $END$&#10;    $trans-&gt;commit();&#10;&#10;    //return true;&#10;} catch (\Exception $e) {&#10;    $trans-&gt;rollBack();&#10;&#10;    //return false;&#10;}" description="Try / Catch" toReformat="true" toShortenFQNames="true">
    <context>
      <option name="PHP" value="true" />
    </context>
  </template>
  <template name="psy" value="eval(\Psy\sh());" description="Psysh runtime developer console" toReformat="false" toShortenFQNames="true">
    <context>
      <option name="PHP" value="true" />
    </context>
  </template>
</templateSet>